[
  {
    "members": [
      {
        "name": "Jaan"
      },
      {
        "name": "Kristiina"
      }
    ]
  },
  {
    "members": [
      {
        "name": "Katre"
      },
      {
        "name": "Gristen"
      },
      {
        "name": "Nana"
      },
      {
        "name": "Eti"
      }
    ]
  },
  {
    "members": [
      {
        "name": "Toomas"
      },
      {
        "name": "Helle"
      }
    ]
  },
  {
    "members": [
      {
        "name": "Emilie"
      }
    ]
  },
  {
    "members": [
      {
        "name": "Villem"
      }
    ]
  },
  {
    "members": [
      {
        "name": "Rasmus"
      },
      {
        "name": "Carmen"
      }
    ]
  }
]
